pu/__init__.py
pu/__main__.py
pu/experiments.py
pu/metrics.py
pu/preprocess.py
pu/zoom.py
pu/models/__init__.py
pu/models/astropt.py
pu/models/base.py
pu/models/hf.py
pu/models/registry.py
pu/pu_datasets/__init__.py
pu/pu_datasets/base.py
pu/pu_datasets/desi.py
pu/pu_datasets/hf_crossmatched.py
pu/pu_datasets/registry.py
pu/pu_datasets/sdss.py
platonic_universe-0.1.0.dist-info/METADATA
platonic_universe-0.1.0.dist-info/WHEEL
platonic_universe-0.1.0.dist-info/entry_points.txt
platonic_universe-0.1.0.dist-info/licenses/LICENSE
platonic_universe-0.1.0.dist-info/RECORD
