Metadata-Version: 2.4
Name: platonic-universe
Version: 0.1.0
Summary: Scripts to test the Platonic Representation Hypothesis on astronomical data
License-File: LICENSE
Requires-Python: >=3.11
Requires-Dist: argparse>=1.4.0
Requires-Dist: astropt>=2.0.5
Requires-Dist: llvmlite>=0.44.0
Requires-Dist: numpy>=2.3.2
Requires-Dist: opencv-python>=4.11.0.86
Requires-Dist: pillow>=11.3.0
Requires-Dist: polars>=1.32.2
Requires-Dist: scikit-image>=0.25.2
Requires-Dist: scikit-learn>=1.7.1
Requires-Dist: torch>=2.8.0
Requires-Dist: transformers>=4.55.0
